<?xml version="1.0" encoding="UTF-8"?><xfdf xmlns="http://ns.adobe.com/xfdf/" xml:space="preserve"><fields/><annots><square page="22" rect="167.960,420.090,254.540,451.260" color="#E44234" flags="print" name="82b3acfb-bb80-68d0-ab61-3f5947ee3e8a" title="Guest" subject="矩形" date="D:20230222082759+08'00'" interior-color="#FFCD45" opacity="0.3409925068639414" creationdate="D:20230222082757+08'00'"/><ink page="22" rect="107.004,325.354,185.636,361.576" color="#E44234" flags="print" name="c12751d9-1b77-d7c3-401c-ba2bffd6be36" title="Guest" subject="手绘" date="D:20230222082815+08'00'" width="2.9562233068944477" creationdate="D:20230222082808+08'00'"><inklist><gesture>109.96,357.75;109.96,357.75;109.96,357.75;109.96,357.75;110.82,357.75;110.82,357.75;110.82,357.75;110.82,357.75;114.29,357.75;116.02,357.75;116.88,357.75;118.61,357.75;120.35,357.75;121.21,357.75;122.08,357.75;122.94,357.75;122.94,357.75;123.81,357.75;124.67,357.75;124.67,357.75;125.54,357.75;125.54,357.75;125.54,357.75;126.41,357.75;126.41,357.75;126.41,357.75</gesture><gesture>118.61,354.28999999999996;118.61,353.41999999999996;118.61,352.56;118.61,350.82;118.61,348.23;119.48,344.76;120.35,341.3;121.21,338.7;122.94,336.97;123.81,335.24;124.67,334.37;125.54,334.37;126.41,333.51;127.27,332.64;128.14,331.78;129,331.78;129.87,330.90999999999997;131.6,330.90999999999997;133.33,330.03999999999996;134.2,329.18;135.93,329.18;137.66,328.31;138.53,328.31;140.26,328.31;141.12,328.31;142.86,328.31;144.59,328.31;149.78,328.31;151.51,328.31;153.25,329.18;154.98,330.03999999999996;156.71,330.03999999999996;157.57,330.90999999999997;158.44,331.78;159.31,331.78;159.31,332.64;160.17,333.51;161.04,334.37;161.9,335.24;162.77,336.11;163.64,336.97;165.37,338.7;166.23,340.43;167.96,342.16999999999996;168.83,344.76;170.56,346.49;171.43,348.23;173.16,350.82;174.02,351.69;174.89,353.41999999999996;174.89,353.41999999999996;175.76,354.28999999999996;175.76,355.15;176.62,355.15;177.49,356.02;177.49,356.02;178.35,356.88;179.22,356.88;179.22,356.88;179.22,356.88;179.22,357.75;180.09,357.75;180.09,357.75;180.95,358.62;180.95,358.62;180.95,358.62;180.95,358.62;180.95,358.62;180.95,358.62;180.09,358.62;180.09,358.62;179.22,358.62;177.49,358.62;176.62,357.75;174.89,357.75;174.02,356.88;172.29,356.88;171.43,356.02;168.83,355.15;167.1,355.15;165.37,354.28999999999996;163.64,354.28999999999996;162.77,354.28999999999996;162.77,354.28999999999996;161.9,354.28999999999996;161.9,354.28999999999996;161.9,354.28999999999996;162.77,354.28999999999996;162.77,355.15;163.64,355.15;164.5,355.15;165.37,355.15;166.23,355.15;167.1,355.15;167.1,355.15;167.96,355.15;168.83,356.02;169.7,356.02;170.56,356.02;172.29,356.02;173.16,356.02;174.02,356.88;174.02,356.88;174.89,356.88;174.89,356.88;175.76,356.88;175.76,356.88;176.62,356.88;178.35,357.75;179.22,357.75;180.09,357.75;180.95,357.75;180.95,357.75;180.95,357.75;180.95,358.62;180.95,357.75;180.95,357.75;180.95,357.75;180.95,356.02;181.82,355.15;181.82,354.28999999999996;181.82,354.28999999999996;181.82,353.41999999999996;181.82,351.69;181.82,349.96000000000004;181.82,348.23;182.68,346.49;182.68,344.76;182.68,343.03;182.68,342.16999999999996;182.68,342.16999999999996;182.68,342.16999999999996;182.68,341.3;182.68,341.3</gesture></inklist></ink><freetext page="22" rect="193.930,376.792,362.755,404.500" flags="print" name="35672ece-003f-8d5a-37cc-e267fda70871" title="Guest" subject="自由文本" date="D:20230222082839+08'00'" width="0" creationdate="D:20230222082815+08'00'" TextColor="#E44234" FontSize="20.710799267846248"><trn-custom-data bytes="{&quot;trn-auto-size-type&quot;:&quot;auto&quot;,&quot;trn-wrapped-text-lines&quot;:&quot;[\&quot;小于这个增长次数 \&quot;]&quot;}"/><contents>小于这个增长次数</contents><contents-richtext><body><p><span style="color:#e44234">小于这个增长次数</span><span/></p></body></contents-richtext><defaultappearance>0 0 0 rg /Helvetica 20.710799267846248 Tf</defaultappearance><defaultstyle>font: Helvetica 20.710799267846248pt; text-align: left; color: #E44234</defaultstyle><apref-replace/></freetext><freetext page="22" rect="357.570,336.972,368.506,362.080" flags="print" name="8db37ab2-ee5f-c0d3-5583-207bf38b639a" title="Guest" subject="自由文本" date="D:20230222082828+08'00'" width="0" creationdate="D:20230222082826+08'00'" TextColor="#E44234" FontSize="20.710799267846248"><trn-custom-data bytes="{&quot;trn-auto-size-type&quot;:&quot;auto&quot;,&quot;trn-wrapped-text-lines&quot;:&quot;[\&quot;在这里插入文字 \&quot;]&quot;}"/><contents/><contents-richtext><body><p><span/></p></body></contents-richtext><defaultappearance>0 0 0 rg /Helvetica 20.710799267846248 Tf</defaultappearance><defaultstyle>font: Helvetica 20.710799267846248pt; text-align: left; color: #E44234</defaultstyle><apref-replace/></freetext><highlight page="22" rect="294.825,173.096,363.400,196.261" color="#FFCD45" flags="print" name="3edc6903-b065-9f07-5565-60a051c8127d" title="Guest" subject="高亮" date="D:20230222083100+08'00'" creationdate="D:20230222083100+08'00'" coords="294.825,196.26070178531245,363.40039893088,196.26070178531245,294.825,173.096250345,363.40039893088,173.096250345"><contents>O(g(n))</contents></highlight><text page="22" rect="294.825,165.261,325.825,196.261" color="#FFFF00" flags="print,nozoom,norotate" inreplyto="3edc6903-b065-9f07-5565-60a051c8127d" name="f2eee57f-4a3c-5515-63bf-62c8bde29fca" title="Guest" subject="注释" date="D:20230222083122+08'00'" creationdate="D:20230222083122+08'00'" icon="Comment" statemodel="Review"><trn-custom-data bytes="{&quot;trn-mention&quot;:&quot;{\&quot;contents\&quot;:\&quot;满足这样函数关系的\&quot;,\&quot;ids\&quot;:[]}&quot;}"/><contents>满足这样函数关系的</contents></text><highlight page="25" rect="61.075,416.408,360.110,437.136" color="#FFCD45" flags="print" name="35301ab7-055a-367b-efc6-6c5ad2f12b8d" title="Guest" subject="高亮" date="D:20230222083304+08'00'" creationdate="D:20230222083304+08'00'" coords="61.07504,437.1360306937501,360.1099986236,437.1360306937501,61.07504,416.4075001725,360.1099986236,416.4075001725"><contents>lΩ (g(n))是增长次数大于等于g(n)</contents></highlight><highlight page="30" rect="116.325,194.025,557.825,219.816" color="#FFCD45" flags="print" name="8c118220-28eb-228d-071c-8bb4930b39d0" title="Guest" subject="高亮" date="D:20230222083353+08'00'" creationdate="D:20230222083353+08'00'" coords="116.32499999999999,219.81600000000003,557.8249999999999,219.81600000000003,116.32499999999999,194.02499999999998,557.8249999999999,194.02499999999998"><contents>g(n)= O(f(n)) ÞO(f(n))+O(g(n)) = O(f(n)) 。</contents></highlight><square page="22" rect="58.010,391.950,677.050,446.490" color="#E44234" flags="print" name="39e6eae8-7fdd-4aec-0de1-b253757ab6d8" title="Guest" subject="矩形" date="D:20230222083511+08'00'" interior-color="#FFCD45" opacity="0.3409925068639414" creationdate="D:20230222083509+08'00'"/><square page="25" rect="44.160,373.770,675.320,449.960" color="#E44234" flags="print" name="aa09486a-1dc8-7d25-60b8-618146ca7f1f" title="Guest" subject="矩形" date="D:20230222083650+08'00'" interior-color="#FFCD45" opacity="0.3409925068639414" creationdate="D:20230222083648+08'00'"/><square page="32" rect="36.360,30.050,658.870,492.380" color="#E44234" flags="print" name="db05cf97-46df-7c7b-d7f9-780f59b2d8be" title="Guest" subject="矩形" date="D:20230222083931+08'00'" interior-color="#FFCD45" opacity="0.3409925068639414" creationdate="D:20230222083922+08'00'"/><square page="31" rect="39.830,451.690,306.490,486.320" color="#E44234" flags="print" name="67586b9f-6b3f-a47d-fc7f-3d6dda4685c0" title="Guest" subject="矩形" date="D:20230222084044+08'00'" interior-color="#FFCD45" opacity="0.3409925068639414" creationdate="D:20230222084042+08'00'"/><square page="31" rect="35.500,111.430,517.750,370.300" color="#000000" flags="print" name="434a06cc-6ef3-7c29-cacc-a6eb33e94367" title="Guest" subject="矩形" date="D:20230222084208+08'00'" interior-color="#272727" opacity="0.06101281269066504" creationdate="D:20230222084141+08'00'"/><square page="35" rect="12.990,59.480,719.480,499.310" color="#000000" flags="print" name="62c1afb0-843c-5ecd-fd80-b80e08414dfb" title="Guest" subject="矩形" date="D:20230222090524+08'00'" interior-color="#272727" opacity="0.06101281269066504" creationdate="D:20230222090521+08'00'"/><square page="36" rect="12.120,101.910,688.310,473.330" color="#000000" flags="print" name="85395e64-1cc5-f887-e45a-5db0919d655b" title="Guest" subject="矩形" date="D:20230222091711+08'00'" interior-color="#272727" opacity="0.06101281269066504" creationdate="D:20230222091707+08'00'"/><square page="37" rect="37.230,219.660,672.720,485.450" color="#000000" flags="print" name="faea1d8f-4877-cd24-6505-a685d090b9b3" title="Guest" subject="矩形" date="D:20230222092341+08'00'" interior-color="#272727" opacity="0.06101281269066504" creationdate="D:20230222092340+08'00'"/><square page="39" rect="42.420,100.180,684.840,468.140" color="#000000" flags="print" name="aa2f9f9b-448d-d020-6193-c78884a55d0e" title="Guest" subject="矩形" date="D:20230222093126+08'00'" interior-color="#272727" opacity="0.06101281269066504" creationdate="D:20230222093124+08'00'"/><square page="47" rect="21.700,337.860,589.150,408.590" color="#000000" flags="print" name="f5e31c05-5f5c-5277-52ac-4a53d95d07b8" title="Guest" subject="矩形" date="D:20230227133526+08'00'" interior-color="#272727" opacity="0.06101281269066504" creationdate="D:20230227133525+08'00'"/><square page="48" rect="31.550,48.740,655.010,438.270" color="#000000" flags="print" name="202508ad-d877-0fa5-4c01-e2e8c12472bb" title="Guest" subject="矩形" date="D:20230227134857+08'00'" interior-color="#272727" opacity="0.06101281269066504" creationdate="D:20230227134855+08'00'"/><square page="54" rect="20.670,86.280,698.530,460.570" color="#000000" flags="print" name="1dfb7623-0699-4dab-bad8-b401429bfcaa" title="Guest" subject="矩形" date="D:20230227135604+08'00'" interior-color="#272727" opacity="0.06101281269066504" creationdate="D:20230227135600+08'00'"/><ink page="56" rect="263.594,230.034,545.046,339.346" color="#E44234" flags="print" name="79f5aac3-1473-f069-2f97-e93cf390b2a6" title="Guest" subject="手绘" date="D:20230227140604+08'00'" width="2.9562233068944477" creationdate="D:20230227140558+08'00'"><inklist><gesture>399.5,304.91999999999996;399.5,304.91999999999996;400.15,304.91999999999996;402.07,304.91999999999996;407.85,304.91999999999996;418.77,304.91999999999996;432.9,304.91999999999996;445.75,304.91999999999996;455.38,304.91999999999996;465.02,304.91999999999996;473.37,304.91999999999996;480.43,304.91999999999996;486.86,304.91999999999996;494.56,304.91999999999996;501.63,304.91999999999996;508.05,304.91999999999996;513.83,304.28;518.97,304.28;524.11,304.28;527.96,304.28;531.82,304.28;534.39,304.91999999999996;535.67,305.56;536.31,306.21000000000004;536.96,306.85;537.6,308.78;538.24,310.7;539.52,313.27;540.81,315.84000000000003;542.09,319.69;542.09,320.98;539.52,322.90999999999997;536.31,324.19;531.82,325.47;526.68,326.76;520.9,328.69;515.12,330.61;508.69,331.9;501.63,333.18;494.56,333.82;486.86,333.82;478.51,333.82;471.44,333.82;464.38,333.82;457.95,333.82;450.89,334.47;444.47,335.11;438.68,335.75;433.55,335.75;428.41,336.39;422.63,336.39;416.85,336.39;412.99,336.39;409.14,335.75;405.93,335.75;403.36,335.11;401.43,334.47;399.5,333.82;398.22,333.18;395.01,330.61;393.72,329.97;393.08,328.69;392.44,328.03999999999996;392.44,326.76;392.44,325.47;392.44,322.26;392.44,317.77;392.44,313.90999999999997;392.44,310.7;393.08,306.85;394.37,303.64;395.65,301.07;396.94,298.5;398.22,296.57;400.15,295.28999999999996;402.72,294.64;405.29,294.64;407.85,294.64;410.42,294.64;411.71,294.64;412.35,294.64;412.99,294.64;412.99,294.64</gesture><gesture>383.45,313.27;384.09,313.27;384.09,313.27;382.16,313.27;376.38,310.7;362.89,303.64;325,277.95;307.66,265.74;294.17,256.11;285.18,249.04000000000002;278.75,245.19;274.9,241.98000000000002;272.97,240.69;268.48,238.12;267.84,237.48000000000002;267.19,237.48000000000002;266.55,237.48000000000002;266.55,236.83999999999997;266.55,236.83999999999997;266.55,236.83999999999997</gesture><gesture>269.76,258.68;269.76,258.68;269.76,258.03;269.12,253.54000000000002;268.48,247.76;267.84,241.98000000000002;267.19,236.83999999999997;267.19,234.26999999999998;267.19,232.99;267.19,232.99;268.48,232.99;271.05,232.99;277.47,232.99;285.18,233.63;291.6,233.63;296.1,234.26999999999998;300.59,234.26999999999998;301.23,234.26999999999998</gesture></inklist></ink><highlight page="56" rect="92.700,223.928,267.712,241.803" color="#FFCD45" flags="print" name="25424bcc-b2fc-a0f7-8844-e947ad5d55d6" title="Guest" subject="高亮" date="D:20230227140613+08'00'" opacity="0.6253813300793166" creationdate="D:20230227140613+08'00'" coords="92.69999759999999,241.80315049914066,267.7119905995201,241.80315049914066,92.69999759999999,223.9275001725,267.7119905995201,223.9275001725"><contents>swap(list[k], list[i]);}</contents></highlight><square page="56" rect="19.820,432.810,323.280,462.150" color="#000000" flags="print" name="8685596a-b110-c8d0-c043-e0ece77d0896" title="Guest" subject="矩形" date="D:20230227141212+08'00'" interior-color="#272727" opacity="0.06101281269066504" creationdate="D:20230227141053+08'00'"/><freetext page="56" rect="190.140,465.271,283.045,490.180" flags="print" name="c7bdc577-796b-8ccd-222d-ce84a62bd12d" title="Guest" subject="自由文本" date="D:20230227141151+08'00'" width="0" creationdate="D:20230227141132+08'00'" TextColor="#E44234" FontSize="20.710799267846248"><trn-custom-data bytes="{&quot;trn-auto-size-type&quot;:&quot;auto&quot;,&quot;trn-wrapped-text-lines&quot;:&quot;[\&quot;函数类型 \&quot;]&quot;}"/><contents>函数类型</contents><contents-richtext><body><p><span style="color:#e44234">函数类型</span><span/></p></body></contents-richtext><defaultappearance>0 0 0 rg /Helvetica 20.710799267846248 Tf</defaultappearance><defaultstyle>font: Helvetica 20.710799267846248pt; text-align: left; color: #E44234</defaultstyle><apref-replace/></freetext><ink page="56" rect="217.904,401.704,306.846,410.106" color="#E44234" flags="print" name="ca2996f5-3190-0603-a74d-dc6afc494ab6" title="Guest" subject="手绘" date="D:20230227141218+08'00'" width="2.9562233068944477" creationdate="D:20230227141215+08'00'"><inklist><gesture>220.86,404.65999999999997;220.86,404.65999999999997;220.86,404.65999999999997;221.69,404.65999999999997;224.18,404.65999999999997;229.16,404.65999999999997;234.14,404.65999999999997;238.29,404.65999999999997;240.79,404.65999999999997;242.45,404.65999999999997;243.28,404.65999999999997;243.28,404.65999999999997;244.11,404.65999999999997;244.11,404.65999999999997;244.11,404.65999999999997;244.11,404.65999999999997;244.94,404.65999999999997;244.94,404.65999999999997;244.94,404.65999999999997;244.94,404.65999999999997;245.77,404.65999999999997;246.6,404.65999999999997;248.26,404.65999999999997;249.09,404.65999999999997;249.92,404.65999999999997;249.92,404.65999999999997;250.75,404.65999999999997;250.75,404.65999999999997</gesture><gesture>276.49,407.15;276.49,407.15;276.49,407.15;276.49,407.15;278.15,407.15;282.3,407.15;288.11,407.15;293.92,407.15;298.08,407.15;301.4,407.15;303.06,407.15;303.89,407.15;303.89,407.15;303.89,407.15;303.89,407.15</gesture></inklist></ink><freetext page="56" rect="201.770,378.931,306.189,403.840" flags="print" name="86a7d049-1c3d-860f-e0da-5c85f8dff5b7" title="Guest" subject="自由文本" date="D:20230227142242+08'00'" width="0" creationdate="D:20230227141219+08'00'" TextColor="#E44234" FontSize="20.710799267846248"><trn-custom-data bytes="{&quot;trn-auto-size-type&quot;:&quot;auto&quot;,&quot;trn-wrapped-text-lines&quot;:&quot;[\&quot;起始位置1 \&quot;]&quot;}"/><contents>起始位置1</contents><contents-richtext><body><p><span style="color:#e44234">起始位置1</span><span/></p></body></contents-richtext><defaultappearance>0 0 0 rg /Helvetica 20.710799267846248 Tf</defaultappearance><defaultstyle>font: Helvetica 20.710799267846248pt; text-align: left; color: #E44234</defaultstyle><apref-replace/></freetext><freetext page="56" rect="157.750,425.411,354.189,450.320" flags="print" name="a2821322-932e-5c05-5a4a-93f1904dca63" title="Guest" subject="自由文本" date="D:20230227143227+08'00'" width="0" creationdate="D:20230227141224+08'00'" TextColor="#E44234" FontSize="20.710799267846248"><trn-custom-data bytes="{&quot;trn-auto-size-type&quot;:&quot;auto&quot;,&quot;trn-wrapped-text-lines&quot;:&quot;[\&quot;数组的最后位置是几 \&quot;]&quot;}"/><contents>数组的最后位置是几</contents><contents-richtext><body><p><span>数组的最后位置是几</span></p></body></contents-richtext><defaultappearance>0 0 0 rg /Helvetica 20.710799267846248 Tf</defaultappearance><defaultstyle>font: Helvetica 20.710799267846248pt; text-align: left; color: #E44234</defaultstyle><apref-replace xmlns="http://www.w3.org/1999/xhtml"></apref-replace></freetext><freetext page="56" rect="364.500,332.421,375.400,357.330" flags="print" name="2df8316e-a874-ea70-2968-7ab1a3b43cb8" title="Guest" subject="自由文本" date="D:20230227141242+08'00'" width="0" creationdate="D:20230227141237+08'00'" TextColor="#E44234" FontSize="20.710799267846248"><trn-custom-data bytes="{&quot;trn-auto-size-type&quot;:&quot;auto&quot;,&quot;trn-wrapped-text-lines&quot;:&quot;[\&quot;在这里插入文字 \&quot;]&quot;}"/><contents/><contents-richtext><body><p><span/></p></body></contents-richtext><defaultappearance>0 0 0 rg /Helvetica 20.710799267846248 Tf</defaultappearance><defaultstyle>font: Helvetica 20.710799267846248pt; text-align: left; color: #E44234</defaultstyle><apref-replace xmlns="http://www.w3.org/1999/xhtml"></apref-replace></freetext><freetext page="56" rect="336.270,318.311,347.170,343.220" flags="print" name="bfc96bd6-3ddf-9c85-4710-34f2f4dd9899" title="Guest" subject="自由文本" date="D:20230227141302+08'00'" width="0" creationdate="D:20230227141248+08'00'" TextColor="#E44234" FontSize="20.710799267846248"><trn-custom-data bytes="{&quot;trn-auto-size-type&quot;:&quot;auto&quot;,&quot;trn-wrapped-text-lines&quot;:&quot;[\&quot;在这里插入文字 \&quot;]&quot;}"/><contents/><contents-richtext><body><p><span/></p></body></contents-richtext><defaultappearance>0 0 0 rg /Helvetica 20.710799267846248 Tf</defaultappearance><defaultstyle>font: Helvetica 20.710799267846248pt; text-align: left; color: #E44234</defaultstyle><apref-replace xmlns="http://www.w3.org/1999/xhtml"></apref-replace></freetext><freetext page="56" rect="19.930,173.836,351.779,183.800" flags="print" name="360cba25-1ba5-f127-7865-7d678bf3eccd" title="Guest" subject="自由文本" date="D:20230227141337+08'00'" width="0" creationdate="D:20230227141331+08'00'" TextColor="#E44234" FontSize="8.160273032336791"><trn-custom-data bytes="{&quot;trn-auto-size-type&quot;:&quot;auto&quot;,&quot;trn-wrapped-text-lines&quot;:&quot;[\&quot;当起始位置 k 等于数组末尾位置 m 时，表示一个排列已经生成完毕，可以进行输出操作； \&quot;]&quot;}"/><contents>当起始位置 k 等于数组末尾位置 m 时，表示一个排列已经生成完毕，可以进行输出操作；</contents><contents-richtext><body><p><span style="color:#e44234">当起始位置 k 等于数组末尾位置 m 时，表示一个排列已经生成完毕，可以进行输出操作；</span><span/></p></body></contents-richtext><defaultappearance>0 0 0 rg /Helvetica 8.160273032336791 Tf</defaultappearance><defaultstyle>font: Helvetica 8.160273032336791pt; text-align: left; color: #E44234</defaultstyle><apref-replace xmlns="http://www.w3.org/1999/xhtml"></apref-replace></freetext><highlight page="57" rect="379.575,437.987,496.316,454.047" color="#FFCD45" flags="print" name="6e2a1ba1-86bc-c515-90b8-0ca4b63acf02" title="Guest" subject="高亮" date="D:20230227144304+08'00'" opacity="0.6253813300793166" creationdate="D:20230227144303+08'00'" coords="379.575,454.0468459375,496.31579999999997,454.0468459375,379.575,437.98688500000003,496.31579999999997,437.98688500000003"><contents>2 perm({1,3,4})</contents></highlight><ink page="57" rect="281.004,273.014,394.856,433.356" color="#E44234" flags="print" name="2cbc7d99-9e8b-25b8-d47d-97682b45b1f7" title="Guest" subject="手绘" date="D:20230227144346+08'00'" width="2.9562233068944477" creationdate="D:20230227144342+08'00'"><inklist><gesture>391.07,430.4;391.9,430.4;391.9,429.57;391.9,428.74;391.07,422.1;388.58,409.64;384.43,393.03999999999996;379.45,376.43;375.29,363.98;372.8,355.66999999999996;371.14,351.52;370.31,348.2;368.65,346.53999999999996;366.99,343.22;364.5,339.07;362.01,335.75;358.69,332.43;357.03,329.1;354.54,325.78;352.05,322.46000000000004;348.72,319.14;345.4,315.82;341.25,312.5;336.27,309.18;331.29,305.86;327.97,303.37;324.65,300.87;321.32,298.38;318,295.89;315.51,293.4;312.19,290.90999999999997;309.7,289.25;308.04,287.59000000000003;306.38,286.76;304.72,285.93;303.06,285.1;301.4,284.27;299.74,283.44;298.08,282.61;296.42,281.78;294.76,280.95;293.92,280.95;292.26,280.12;291.43,279.29;290.6,279.29;289.77,278.46;289.77,278.46;288.94,277.63;288.94,277.63;288.11,276.8;288.11,276.8</gesture><gesture>293.09,287.59000000000003;293.09,287.59000000000003;293.09,286.76;292.26,285.93;291.43,285.1;289.77,283.44;288.94,281.78;287.28,280.95;286.45,280.12;285.62,279.29;285.62,278.46;284.79,277.63;283.96,277.63;283.96,276.8;283.96,276.8;283.96,275.97;283.96,275.97;283.96,275.97;284.79,275.97;286.45,275.97;287.28,275.97;288.94,275.97;290.6,275.97;293.09,276.8;295.59,276.8;298.08,277.63;300.57,277.63;303.06,277.63;304.72,277.63;306.38,277.63;307.21,277.63;308.04,276.8;308.04,276.8</gesture></inklist></ink><square page="58" rect="49.780,46.070,692.490,439.890" color="#000000" flags="print" name="741c5ede-0c96-7c04-6ae7-8495fa246e07" title="Guest" subject="矩形" date="D:20230306140005+08'00'" interior-color="#272727" opacity="0.06101281269066504" creationdate="D:20230306140003+08'00'"/><square page="59" rect="55.310,31.690,703.560,31.710" color="#000000" flags="print" name="0ab4af7c-97fb-440b-25c2-d31d38d2b38f" title="Guest" subject="矩形" date="D:20230306141356+08'00'" interior-color="#272727" opacity="0.06101281269066504" creationdate="D:20230306140731+08'00'"/><ink page="59" rect="310.104,186.924,356.946,216.066" color="#E44234" flags="print" name="8f1e15ee-c6f5-d283-ad71-32cb051555d3" title="Guest" subject="手绘" date="D:20230306141413+08'00'" width="2.9562233068944477" creationdate="D:20230306141411+08'00'"><inklist><gesture>313.06,213.11;313.06,213.11;314.17,213.11;317.49,210.89999999999998;325.23,207.57999999999998;334.08,202.05;341.82,197.62;347.35,194.31;351.78,190.99;352.88,189.88;353.99,189.88</gesture></inklist></ink><freetext page="59" rect="418.150,188.773,468.727,213.110" flags="print" name="59b5b91c-2118-8037-d7ca-e34eb8d8be83" title="Guest" subject="自由文本" date="D:20230306141442+08'00'" width="0" creationdate="D:20230306141428+08'00'" TextColor="#E44234" FontSize="20.25320317266626"><trn-custom-data bytes="{&quot;trn-auto-size-type&quot;:&quot;auto&quot;,&quot;trn-wrapped-text-lines&quot;:&quot;[\&quot;大于 \&quot;]&quot;}"/><contents>大于</contents><contents-richtext><body><p><span style="color:#e44234">大于</span><span/></p></body></contents-richtext><defaultappearance>0 0 0 rg /Helvetica 20.25320317266626 Tf</defaultappearance><defaultstyle>font: Helvetica 20.25320317266626pt; text-align: left; color: #E44234</defaultstyle><apref-replace xmlns="http://www.w3.org/1999/xhtml"></apref-replace></freetext><square page="79" rect="15.490,96.410,680.330,491.330" color="#000000" flags="print" name="7486d0c3-ad41-7b5d-e234-9ef81eefacf8" title="Guest" subject="矩形" date="D:20230308133145+08'00'" interior-color="#272727" opacity="0.06101281269066504" creationdate="D:20230308133144+08'00'"/></annots><pages><defmtx matrix="1,0,0,-1,0,540"/></pages></xfdf>